pubsub/__init__.py
pubsub/adapters.py
pubsub/test.py
pubsub_validators.py-0.1.0.dist-info/DESCRIPTION.rst
pubsub_validators.py-0.1.0.dist-info/METADATA
pubsub_validators.py-0.1.0.dist-info/RECORD
pubsub_validators.py-0.1.0.dist-info/WHEEL
pubsub_validators.py-0.1.0.dist-info/metadata.json
pubsub_validators.py-0.1.0.dist-info/top_level.txt
validators/__init__.py
validators/validator.py
