Metadata-Version: 2.0
Name: pubsub-validators.py
Version: 0.1.0
Summary: Python PubSub Validators  for gcloud, redis and kafka
Home-page: https://github.com/Superbalist/python-pubsub-validators
Author: Superbalist Engineering
Author-email: tech@superbalist.com
License: UNKNOWN
Platform: UNKNOWN
Requires-Dist: jsonschema
